dbh_pyutils/__init__.py
dbh_pyutils/dbh_chroma.py
dbh_pyutils/dbh_nlp.py
dbh_pyutils/dbh_prompt_builder.py
dbh_pyutils/dbh_stable_diffusion_api.py
dbh_pyutils/dbh_text_generation_webui_api.py
dbh_pyutils/dbh_vidsquid_markup.py
dbh_pyutils/dbh_whisper.py
dbh_pyutils/dbh_youtube.py
dbh_pyutils-0.1.4.dist-info/LICENSE
dbh_pyutils-0.1.4.dist-info/METADATA
dbh_pyutils-0.1.4.dist-info/WHEEL
dbh_pyutils-0.1.4.dist-info/top_level.txt
dbh_pyutils-0.1.4.dist-info/RECORD
