Metadata-Version: 2.1
Name: dbh-pyutils
Version: 0.1.4
Summary: DBH Utils Python library
Home-page: https://github.com/deevis/dbh-pyutils
Author: Darren Hicks
Author-email: darren.hicks@gmail.com
License: MIT
Requires-Python: >=3.10
License-File: LICENSE
Requires-Dist: chromadb
Requires-Dist: pytube
Requires-Dist: nltk
Requires-Dist: langchain
